{
      "Basic Info": {
            "Name": "Adani Ports and Special Economic Zone Limited",
            "Symbol": "ADANIPORTS.NS",
            "Current Price": "693.55",
            "Change Percent": "-0.17%",
            "52 Week High": "901.00",
            "52 Week Low": "312.10",
            "Deliverable to Traded Quantity Percent": "82.9%"
      },
      "Technical Indicators": {
            "RSI": 48.5575,
            "ADX": 19.727,
            "MACD": [
                  {
                        "Line": -9.5836
                  },
                  {
                        "Signal": -14.0016
                  }
            ],
            "OBV": 974256291.0,
            "MFI": 42.8141,
            "50 day volume trend": "",
            "MOMSQZE": ""
      }
}