{
      "Basic Info": {
            "Name": "Apollo Hospitals Enterprise Limited",
            "Symbol": "APOLLOHOSP.NS",
            "Current Price": "4,713.00",
            "Change Percent": "-0.41%",
            "52 Week High": "5,122.00",
            "52 Week Low": "1,678.05",
            "Deliverable to Traded Quantity Percent": "41.46%"
      },
      "Technical Indicators": {
            "RSI": 54.5271,
            "ADX": 41.966,
            "MACD": [
                  {
                        "Line": 141.1666
                  },
                  {
                        "Signal": 199.1135
                  }
            ],
            "OBV": 242602452.0,
            "MFI": 53.0129,
            "50 day volume trend": false,
            "MOMSQZE": "TRND"
      }
}