{
      "Basic Info": {
            "Name": "Asian Paints Limited",
            "Symbol": "ASIANPAINT.NS",
            "Current Price": "3,305.90",
            "Change Percent": "0.46%",
            "52 Week High": "3,505.00",
            "52 Week Low": "2,041.25",
            "Deliverable to Traded Quantity Percent": "NA"
      },
      "Technical Indicators": {
            "RSI": 54.0021,
            "ADX": 27.7759,
            "MACD": [
                  {
                        "Line": 14.1918
                  },
                  {
                        "Signal": 30.0876
                  }
            ],
            "OBV": 441429260.0,
            "MFI": 61.4225,
            "50 day volume trend": false,
            "MOMSQZE": "TRND",
            "10 day MA": 3281.85
      }
}