{
      "Basic Info": {
            "Name": "Colgate-Palmolive (India) Limited",
            "Symbol": "COLPAL.NS",
            "Current Price": "1,645.85",
            "Change Percent": "-0.75%",
            "52 Week High": "1,823.40",
            "52 Week Low": "1,322.15",
            "Deliverable to Traded Quantity Percent": "NA"
      },
      "Technical Indicators": {
            "RSI": 34.8936,
            "ADX": 29.3905,
            "MACD": [
                  {
                        "Line": -19.1003
                  },
                  {
                        "Signal": -8.195
                  }
            ],
            "OBV": 144972665.0,
            "MFI": 26.9901,
            "50 day volume trend": true,
            "MOMSQZE": "TRNDd"
      }
}