{
      "Basic Info": {
            "Name": "Dr. Reddy's Laboratories Limited",
            "Symbol": "DRREDDY.NS",
            "Current Price": "4,513.90",
            "Change Percent": "-0.77%",
            "52 Week High": "5,614.60",
            "52 Week Low": "4,135.00",
            "Deliverable to Traded Quantity Percent": "NA"
      },
      "Technical Indicators": {
            "RSI": 28.3456,
            "ADX": 41.0451,
            "MACD": [
                  {
                        "Line": -157.021
                  },
                  {
                        "Signal": -157.5613
                  }
            ],
            "OBV": 231841731.0,
            "MFI": 39.5923,
            "50 day volume trend": false,
            "MOMSQZE": "SQZE"
      }
}