{
      "Basic Info": {
            "Name": "Hindustan Petroleum Corporation Limited",
            "Symbol": "HINDPETRO.NS",
            "Current Price": "324.75",
            "Change Percent": "1.79%",
            "52 Week High": "326.75",
            "52 Week Low": "162.90",
            "Deliverable to Traded Quantity Percent": "51.49%"
      },
      "Technical Indicators": {
            "RSI": 77.3719,
            "ADX": 47.9495,
            "MACD": [
                  {
                        "Line": 13.4845
                  },
                  {
                        "Signal": 10.5761
                  }
            ],
            "OBV": 2730181243.0,
            "MFI": 94.0661,
            "50 day volume trend": false,
            "MOMSQZE": "TRNDu",
            "10 day MA": 310.80499877929685
      }
}