{
      "Basic Info": {
            "Name": "Indraprastha Gas Limited",
            "Symbol": "IGL.NS",
            "Current Price": "561.35",
            "Change Percent": "-1.66%",
            "52 Week High": "602.05",
            "52 Week Low": "364.10",
            "Deliverable to Traded Quantity Percent": "NA"
      },
      "Technical Indicators": {
            "RSI": 53.0934,
            "ADX": 31.6326,
            "MACD": [
                  {
                        "Line": 10.0693
                  },
                  {
                        "Signal": 8.1473
                  }
            ],
            "OBV": 1646876099.0,
            "MFI": 81.2387,
            "50 day volume trend": false,
            "MOMSQZE": "TRNDu"
      }
}