{
      "Basic Info": {
            "Name": "Indraprastha Gas Limited",
            "Symbol": "IGL.NS",
            "Current Price": "546.30",
            "Change Percent": "0.08%",
            "52 Week High": "594.85",
            "52 Week Low": "364.10",
            "Deliverable to Traded Quantity Percent": "NA"
      },
      "Technical Indicators": {
            "RSI": 58.9375,
            "ADX": 13.5001,
            "MACD": [
                  {
                        "Line": -1.8566
                  },
                  {
                        "Signal": -4.1054
                  }
            ],
            "OBV": 1650618019.0,
            "MFI": 72.3229,
            "50 day volume trend": false,
            "MOMSQZE": "SQZE"
      }
}