{
      "Basic Info": {
            "Name": "Infosys Limited",
            "Symbol": "INFY.NS",
            "Current Price": "1,668.95",
            "Change Percent": "-0.58%",
            "52 Week High": "1,788.00",
            "52 Week Low": "1,031.35",
            "Deliverable to Traded Quantity Percent": "NA"
      },
      "Technical Indicators": {
            "RSI": 43.9672,
            "ADX": 19.9808,
            "MACD": [
                  {
                        "Line": -2.2586
                  },
                  {
                        "Signal": 5.1074
                  }
            ],
            "OBV": 3992301060.0,
            "MFI": 33.1511,
            "50 day volume trend": false,
            "MOMSQZE": "SQZE",
            "10 day MA": 1701.3400024414063
      }
}