{
      "Basic Info": {
            "Name": "ITC Limited",
            "Symbol": "ITC.NS",
            "Current Price": "211.15",
            "Change Percent": "-0.59%",
            "52 Week High": "239.20",
            "52 Week Low": "163.35"
      },
      "Technical Indicators": {
            "RSI": 65.1679,
            "ADX": 23.0494,
            "MACD": [
                  {
                        "Line": 0.9594
                  },
                  {
                        "Signal": -0.1515
                  }
            ],
            "OBV": "",
            "MFI": ""
      }
}