{
      "Basic Info": {
            "Name": "JK Paper Ltd",
            "Symbol": "JKPAPER.NS",
            "Current Price": "246.15",
            "Change Percent": "-0.10%",
            "52 Week High": "284.90",
            "52 Week Low": "86.30",
            "Deliverable to Traded Quantity Percent": "NA"
      },
      "Technical Indicators": {
            "RSI": 54.9055,
            "ADX": 17.5027,
            "MACD": [
                  {
                        "Line": 0.6094
                  },
                  {
                        "Signal": -1.2238
                  }
            ],
            "OBV": 489676720.0,
            "MFI": 67.1665,
            "50 day volume trend": false,
            "MOMSQZE": "TRNDu",
            "10 day MA": 238.40999908447264
      }
}