{
      "Basic Info": {
            "Name": "JSW Steel Limited",
            "Symbol": "JSWSTEEL.NS",
            "Current Price": "679.00",
            "Change Percent": "1.50%",
            "52 Week High": "776.50",
            "52 Week Low": "257.55",
            "Deliverable to Traded Quantity Percent": "NA"
      },
      "Technical Indicators": {
            "RSI": 46.476,
            "ADX": 24.3504,
            "MACD": [
                  {
                        "Line": -10.0183
                  },
                  {
                        "Signal": -8.8628
                  }
            ],
            "OBV": 3773022167.0,
            "MFI": 51.5982,
            "50 day volume trend": true,
            "MOMSQZE": "SQZE"
      }
}