{
      "Basic Info": {
            "Name": "Lupin Limited",
            "Symbol": "LUPIN.NS",
            "Current Price": "952.70",
            "Change Percent": "0.57%",
            "52 Week High": "1,267.65",
            "52 Week Low": "855.35",
            "Deliverable to Traded Quantity Percent": "NA"
      },
      "Technical Indicators": {
            "RSI": 45.479,
            "ADX": 28.0484,
            "MACD": [
                  {
                        "Line": -9.1937
                  },
                  {
                        "Signal": -12.9029
                  }
            ],
            "OBV": 856035726.0,
            "MFI": 69.1039,
            "50 day volume trend": false,
            "MOMSQZE": "SQZE",
            "10 day MA": 954.3599975585937
      }
}