{
      "Basic Info": {
            "Name": "Max Healthcare Institute Limited",
            "Symbol": "MAXHEALTH.NS",
            "Current Price": "347.50",
            "Change Percent": "-0.87%",
            "52 Week High": "402.60",
            "52 Week Low": "97.15",
            "Deliverable to Traded Quantity Percent": "31.19%"
      },
      "Technical Indicators": {
            "RSI": 43.6422,
            "ADX": 23.1339,
            "MACD": [
                  {
                        "Line": -0.9309
                  },
                  {
                        "Signal": 3.6968
                  }
            ],
            "OBV": 4082197.0,
            "MFI": 5.0215,
            "50 day volume trend": false,
            "MOMSQZE": "TRNDd",
            "10 day MA": 355.2549987792969
      }
}