{
      "Basic Info": {
            "Name": "MRF Limited",
            "Symbol": "MRF.NS",
            "Current Price": "80,065.80",
            "Change Percent": "0.80%",
            "52 Week High": "98,599.95",
            "52 Week Low": "63,502.10",
            "Deliverable to Traded Quantity Percent": "NA"
      },
      "Technical Indicators": {
            "RSI": 44.5656,
            "ADX": 17.5494,
            "MACD": [
                  {
                        "Line": 210.8675
                  },
                  {
                        "Signal": 707.8291
                  }
            ],
            "OBV": 5667644.0,
            "MFI": 41.6235,
            "50 day volume trend": false,
            "MOMSQZE": "TRNDd",
            "10 day MA": 82811.2109375
      }
}