{
      "Basic Info": {
            "Name": "Page Industries Limited",
            "Symbol": "PAGEIND.NS",
            "Current Price": "31,408.30",
            "Change Percent": "-0.05%",
            "52 Week High": "33,989.00",
            "52 Week Low": "17,685.00",
            "Deliverable to Traded Quantity Percent": "46.4%"
      },
      "Technical Indicators": {
            "RSI": 49.8083,
            "ADX": 16.1315,
            "MACD": [
                  {
                        "Line": -213.3878
                  },
                  {
                        "Signal": -174.3396
                  }
            ],
            "OBV": 17265685.0,
            "MFI": 45.7935,
            "50 day volume trend": false,
            "MOMSQZE": "TRND"
      }
}