{
      "Basic Info": {
            "Name": "State Bank of India",
            "Symbol": "SBIN.NS",
            "Current Price": "429.80",
            "Change Percent": "0.88%",
            "52 Week High": "467.45",
            "52 Week Low": "175.50",
            "Deliverable to Traded Quantity Percent": "57.03%"
      },
      "Technical Indicators": {
            "RSI": 54.5429,
            "ADX": 14.9141,
            "MACD": [
                  {
                        "Line": -2.0208
                  },
                  {
                        "Signal": -2.6522
                  }
            ],
            "OBV": 11886480328.0,
            "MFI": 40.7665,
            "50 day volume trend": false,
            "MOMSQZE": "TRND"
      }
}