{
      "Basic Info": {
            "Name": "State Bank of India",
            "Symbol": "SBIN.NS",
            "Current Price": "494.55",
            "Change Percent": "-0.59%",
            "52 Week High": "549.00",
            "52 Week Low": "321.30",
            "Deliverable to Traded Quantity Percent": "NA"
      },
      "Technical Indicators": {
            "RSI": 52.8491,
            "ADX": 17.9856,
            "MACD": [
                  {
                        "Line": -0.1048
                  },
                  {
                        "Signal": -3.3708
                  }
            ],
            "OBV": 12458180463.0,
            "MFI": 78.3074,
            "50 day volume trend": false,
            "MOMSQZE": "TRNDu",
            "10 day MA": 492.52500305175784
      }
}