{
      "Basic Info": {
            "Name": "Shree Cement Limited",
            "Symbol": "SHREECEM.NS",
            "Current Price": "30,842.20",
            "Change Percent": "0.60%",
            "52 Week High": "32,048.00",
            "52 Week Low": "18,183.55",
            "Deliverable to Traded Quantity Percent": "60.89%"
      },
      "Technical Indicators": {
            "RSI": 76.0167,
            "ADX": 35.8886,
            "MACD": [
                  {
                        "Line": 934.0279
                  },
                  {
                        "Signal": 650.489
                  }
            ],
            "OBV": 20084326.0,
            "MFI": 85.0604,
            "50 day volume trend": false,
            "MOMSQZE": "TRNDu"
      }
}