{
      "Basic Info": {
            "Name": "Shree Cement Limited",
            "Symbol": "SHREECEM.NS",
            "Current Price": "28,452.65",
            "Change Percent": "0.58%",
            "52 Week High": "32,048.00",
            "52 Week Low": "18,183.55",
            "Deliverable to Traded Quantity Percent": "NA"
      },
      "Technical Indicators": {
            "RSI": 63.7933,
            "ADX": 20.0989,
            "MACD": [
                  {
                        "Line": -83.6645
                  },
                  {
                        "Signal": -317.6741
                  }
            ],
            "OBV": 19651106.0,
            "MFI": 59.8733,
            "50 day volume trend": false,
            "MOMSQZE": "TRNDu"
      }
}