{
      "Basic Info": {
            "Name": "Tata Motors Limited",
            "Symbol": "TATAMOTORS.NS",
            "Current Price": "289.30",
            "Change Percent": "0.70%",
            "52 Week High": "360.75",
            "52 Week Low": "122.15",
            "Deliverable to Traded Quantity Percent": "51.32%"
      },
      "Technical Indicators": {
            "RSI": 44.7931,
            "ADX": 24.2832,
            "MACD": [
                  {
                        "Line": -5.1966
                  },
                  {
                        "Signal": -5.8113
                  }
            ],
            "OBV": 9065518443.0,
            "MFI": 40.3085,
            "50 day volume trend": false,
            "MOMSQZE": "TRNDd"
      }
}