{
      "Basic Info": {
            "Name": "Tata Steel Limited",
            "Symbol": "TATASTEEL.NS",
            "Current Price": "1,461.65",
            "Change Percent": "1.83%",
            "52 Week High": "1,481.80",
            "52 Week Low": "342.75",
            "Deliverable to Traded Quantity Percent": "NA"
      },
      "Technical Indicators": {
            "RSI": 67.9742,
            "ADX": 36.5115,
            "MACD": [
                  {
                        "Line": 59.0174
                  },
                  {
                        "Signal": 60.3119
                  }
            ],
            "OBV": 4234558500.0,
            "MFI": 82.1839,
            "50 day volume trend": true,
            "MOMSQZE": "TRNDu"
      }
}