{
      "Basic Info": {
            "Name": "Tech Mahindra Limited",
            "Symbol": "TECHM.NS",
            "Current Price": "1,406.90",
            "Change Percent": "1.53%",
            "52 Week High": "1,547.85",
            "52 Week Low": "781.85",
            "Deliverable to Traded Quantity Percent": "NA"
      },
      "Technical Indicators": {
            "RSI": 48.5891,
            "ADX": 31.3331,
            "MACD": [
                  {
                        "Line": 0.2034
                  },
                  {
                        "Signal": 12.717
                  }
            ],
            "OBV": 1459241786.0,
            "MFI": 37.3949,
            "50 day volume trend": false,
            "MOMSQZE": "TRNDd",
            "10 day MA": 1414.4500122070312
      }
}