{
      "Basic Info": {
            "Name": "Titan Company Limited",
            "Symbol": "TITAN.NS",
            "Current Price": "2,077.95",
            "Change Percent": "-0.84%",
            "52 Week High": "2,150.00",
            "52 Week Low": "1,076.00",
            "Deliverable to Traded Quantity Percent": "55.63%"
      },
      "Technical Indicators": {
            "RSI": 70.5125,
            "ADX": 50.6926,
            "MACD": [
                  {
                        "Line": 74.0062
                  },
                  {
                        "Signal": 68.3675
                  }
            ],
            "OBV": 4444623336.0,
            "MFI": 77.2925,
            "50 day volume trend": false,
            "MOMSQZE": "TRNDu"
      }
}