{
      "Basic Info": {
            "Name": "UltraTech Cement Limited",
            "Symbol": "ULTRACEMCO.NS",
            "Current Price": "7,610.00",
            "Change Percent": "0.45%",
            "52 Week High": "8,073.30",
            "52 Week Low": "3,753.90",
            "Deliverable to Traded Quantity Percent": "NA"
      },
      "Technical Indicators": {
            "RSI": 45.8354,
            "ADX": 24.1032,
            "MACD": [
                  {
                        "Line": 53.4008
                  },
                  {
                        "Signal": 101.3087
                  }
            ],
            "OBV": 107708616.0,
            "MFI": 47.3011,
            "50 day volume trend": false,
            "MOMSQZE": "TRNDd"
      }
}